CHANGES.txt
INSTALL.txt
LICENSE.txt
MANIFEST.in
README.txt
setup.py
NanoCap.egg-info/PKG-INFO
NanoCap.egg-info/SOURCES.txt
NanoCap.egg-info/dependency_links.txt
NanoCap.egg-info/requires.txt
NanoCap.egg-info/top_level.txt
bin/nanocap
docs/NanoCap.pdf
docs/html/Code.html
docs/html/Examples.html
docs/html/Optimisation.html
docs/html/Rendering.html
docs/html/__init__.py
docs/html/cappednanotubes.html
docs/html/chm.hhc
docs/html/chm.hhk
docs/html/chm.hhp
docs/html/dforcefields.html
docs/html/eclipse-index.xml
docs/html/eclipse-plugin.xml
docs/html/eclipse-toc.xml
docs/html/forcefields.html
docs/html/index.html
docs/html/javahelp1-toc.xml
docs/html/javahelp1.hs
docs/html/javahelp1.jhm
docs/html/javahelp2-toc.xml
docs/html/javahelp2.hs
docs/html/javahelp2.jhm
docs/html/sect0001.html
docs/html/sect0002.html
docs/html/sect0003.html
docs/html/sect0004.html
docs/html/sect0005.html
docs/html/sect0006.html
docs/html/sect0007.html
docs/html/sect0008.html
docs/html/sect0009.html
docs/html/sect0010.html
docs/html/sect0011.html
docs/html/sect0012.html
docs/html/sect0013.html
docs/html/sect0014.html
docs/html/sect0015.html
docs/html/sect0016.html
docs/html/sect0017.html
docs/html/sect0018.html
docs/html/sect0019.html
docs/html/sect0020.html
docs/html/sect0021.html
docs/html/sect0022.html
docs/html/sect0023.html
docs/html/.cache/DVIPNG.images
docs/html/images/img-0001.png
docs/html/images/img-0002.png
docs/html/images/img-0003.png
docs/html/images/img-0004.png
docs/html/images/img-0005.png
docs/html/images/img-0006.png
docs/html/images/img-0007.png
docs/html/images/img-0008.png
docs/html/images/img-0009.png
docs/html/images/img-0010.png
docs/html/images/img-0011.png
docs/html/images/img-0012.png
docs/html/images/img-0013.png
docs/html/images/img-0014.png
docs/html/images/img-0015.png
docs/html/images/img-0016.png
docs/html/images/img-0017.png
docs/html/images/img-0018.png
docs/html/images/img-0019.png
docs/html/images/img-0020.png
docs/html/images/img-0021.png
docs/html/images/img-0022.png
docs/html/images/img-0023.png
docs/html/images/img-0024.png
docs/html/images/img-0025.png
docs/html/images/img-0026.png
