Metadata-Version: 1.0
Name: NanoCap
Version: 1.0b12
Summary: Application and libraries for the generation of carbon fullerenes, nanotubes and capped nanotubes
Home-page: http://sourceforge.net/projects/nanocap/
Author: Marc Robinson
Author-email: marcrobinson85@gmail.com
License: CC-NC Creative Commons Non-Commercial
Platform: UNKNOWN
